desec/__init__.py
desec/__main__.py
desec/api.py
desec/cli.py
desec/exceptions.py
desec/py.typed
desec/tlsa.py
desec/types.py
desec/utils.py
desec_dns-1.3.0.dist-info/LICENSE
desec_dns-1.3.0.dist-info/METADATA
desec_dns-1.3.0.dist-info/WHEEL
desec_dns-1.3.0.dist-info/entry_points.txt
desec_dns-1.3.0.dist-info/RECORD
