Metadata-Version: 2.3
Name: desec-dns
Version: 1.3.0
Summary: A simple deSEC.io API client
License: MIT
Author: Sebastian Hamann
Author-email: code@ares-macrotechnology.com
Requires-Python: >=3.9
Classifier: Environment :: Console
Classifier: License :: OSI Approved :: MIT License
Classifier: Operating System :: OS Independent
Classifier: Programming Language :: Python :: 3
Classifier: Programming Language :: Python :: 3.9
Classifier: Programming Language :: Python :: 3.10
Classifier: Programming Language :: Python :: 3.11
Classifier: Programming Language :: Python :: 3.12
Classifier: Programming Language :: Python :: 3.13
Classifier: Typing :: Typed
Provides-Extra: all
Provides-Extra: tlsa
Provides-Extra: zonefiles
Requires-Dist: cryptography (>=42.0.0) ; extra == "tlsa" or extra == "all"
Requires-Dist: dnspython (>=2.0.0) ; extra == "zonefiles" or extra == "all"
Requires-Dist: requests (>=2.0.0)
Project-URL: Changelog, https://github.com/s-hamann/desec-dns/blob/main/CHANGELOG.md
Project-URL: Documentation, https://s-hamann.github.io/desec-dns/
Project-URL: Issue Tracker, https://github.com/s-hamann/desec-dns/issues
Project-URL: Repository, https://github.com/s-hamann/desec-dns
